av1an.py
av1an/__init__.py
av1an/__main__.py
av1an/arg_parse.py
av1an/commandtypes.py
av1an/concat.py
av1an/fp_reuse.py
av1an/logger.py
av1an/resume.py
av1an/split.py
av1an/utils.py
av1an/vapoursynth.py
av1an/chunk/Chunk.py
av1an/chunk/__init__.py
av1an/chunk/chunk_queue.py
av1an/encoder/__init__.py
av1an/encoder/aom.py
av1an/encoder/encoder.py
av1an/encoder/rav1e.py
av1an/encoder/svtav1.py
av1an/encoder/svtvp9.py
av1an/encoder/vpx.py
av1an/encoder/vvc.py
av1an/encoder/x264.py
av1an/encoder/x265.py
av1an/ffmpeg/__init__.py
av1an/ffmpeg/ffmpeg.py
av1an/manager/Counter.py
av1an/manager/Manager.py
av1an/manager/Pipes.py
av1an/manager/Queue.py
av1an/manager/__init__.py
av1an/project/Project.py
av1an/project/__init__.py
av1an/scenedetection/__init__.py
av1an/scenedetection/aom_kf.py
av1an/scenedetection/ffmpeg.py
av1an/scenedetection/pyscene.py
av1an/startup/__init__.py
av1an/startup/file_validation.py
av1an/startup/setup.py
av1an/startup/validate_commands.py
av1an/target_quality/__init__.py
av1an/target_quality/target_quality.py
av1an/vmaf/__init__.py
av1an/vmaf/vmaf.py
Av1an-6.1.5.dist-info/LICENSE.md
Av1an-6.1.5.dist-info/METADATA
Av1an-6.1.5.dist-info/WHEEL
Av1an-6.1.5.dist-info/entry_points.txt
Av1an-6.1.5.dist-info/top_level.txt
Av1an-6.1.5.dist-info/RECORD
